pystof/__init__.py
pystof/pystof.cp314-win_amd64.pyd
stof-0.9.6.dist-info/METADATA
stof-0.9.6.dist-info/WHEEL
stof-0.9.6.dist-info/licenses/LICENSE
stof-0.9.6.dist-info/RECORD
