Metadata-Version: 2.4
Name: stof
Version: 0.9.6
Classifier: Programming Language :: Rust
Classifier: Programming Language :: Python :: Implementation :: CPython
Classifier: Programming Language :: Python :: Implementation :: PyPy
License-File: LICENSE
Summary: Data that carries its own logic.
Keywords: format,runtime,validation,embedded
Home-Page: https://docs.stof.dev
Author-email: CJ Cummings <cj@stof.dev>
License-Expression: Apache-2.0
Requires-Python: >=3.7
Project-URL: Documentation, https://docs.stof.dev
Project-URL: Playground, https://play.stof.dev
Project-URL: Repository, https://github.com/dev-formata-io/stof
